{"puzzle_id": 21363, "promo_id": null, "version": 0, "puzzle_meta": {"formatType": "Normal", "publishType": "Daily", "title": "", "printDate": "2023-10-03", "printDotw": 2, "editor": "Will Shortz", "copyright": "", "height": 15, "width": 15, "notes": [], "links": [], "layoutExtra": [], "author": "Troy Laedtke", "relatedContent": {"text": "Read and comment on the Wordplay blog", "url": "https://www.nytimes.com/2023/10/02/crosswords/daily-puzzle-2023-10-03.html"}}, "print_date": "2023-10-03", "enhanced_tier_date": null, "authors": ["Troy Laedtke"], "puzzle_data": {"clues": {"A": [{"clueNum": 1, "clueStart": 0, "value": "Gave up a seat, maybe", "clueEnd": 4}, {"clueNum": 6, "clueStart": 7, "value": "Apathetic reaction", "clueEnd": 9}, {"clueNum": 9, "clueStart": 12, "value": "MTV prize whose trophy features an astronaut", "clueEnd": 14}, {"clueNum": 12, "clueStart": 15, "value": "Bea Arthur sitcom of the 1970s", "clueEnd": 19}, {"clueNum": 13, "clueStart": 21, "value": "Like the \"legs\" on a 48-Down", "clueEnd": 29, "related": {"down": [48], "across": []}}, {"clueNum": 16, "clueStart": 30, "value": "John who sang \"Crocodile Rock\"", "clueEnd": 34, "formatted": "John who sang \"Crocodile Rock\""}, {"clueNum": 17, "clueStart": 36, "value": "Teaches", "clueEnd": 44}, {"clueNum": 18, "clueStart": 45, "value": "In the open air, as a meal", "clueEnd": 52}, {"clueNum": 20, "clueStart": 54, "value": "Ancient inhabitant of Scotland", "clueEnd": 57}, {"clueNum": 21, "clueStart": 60, "value": "Co-op that sells camping gear ", "clueEnd": 62}, {"clueNum": 22, "clueStart": 64, "value": "Wild pigs", "clueEnd": 68}, {"clueNum": 24, "clueStart": 70, "value": "Number in the Gettysburg Address", "clueEnd": 74}, {"clueNum": 27, "clueStart": 75, "value": "Mlle. : French :: ___ : Spanish", "clueEnd": 78}, {"clueNum": 29, "clueStart": 80, "value": "Frustrated cries", "clueEnd": 84}, {"clueNum": 31, "clueStart": 86, "value": "Certain nest eggs, in brief", "clueEnd": 89}, {"clueNum": 32, "clueStart": 93, "value": "Crime lab evidence", "clueEnd": 95}, {"clueNum": 34, "clueStart": 97, "value": "Composer Zimmer who won Oscars for \"The Lion King\" and \"Dune\"", "clueEnd": 100}, {"clueNum": 36, "clueStart": 102, "value": "Little troublemaker", "clueEnd": 104}, {"clueNum": 37, "clueStart": 105, "value": "Frustrating find while folding laundry", "clueEnd": 111}, {"clueNum": 41, "clueStart": 113, "value": "Brush up on old skills", "clueEnd": 119}, {"clueNum": 43, "clueStart": 120, "value": "___ State (Idaho nickname)", "clueEnd": 122}, {"clueNum": 44, "clueStart": 124, "value": "\"S.N.L.\" alum Carvey", "clueEnd": 127}, {"clueNum": 46, "clueStart": 129, "value": "Lead-in to mode", "clueEnd": 131}, {"clueNum": 47, "clueStart": 135, "value": "Sewing targets", "clueEnd": 138}, {"clueNum": 49, "clueStart": 140, "value": "Native language in Oslo", "clueEnd": 144}, {"clueNum": 51, "clueStart": 146, "value": "Mount Olympus figures", "clueEnd": 149}, {"clueNum": 55, "clueStart": 150, "value": "Justice Kagan", "clueEnd": 154}, {"clueNum": 57, "clueStart": 156, "value": "\"La ___\" (1958 Ritchie Valens hit)", "clueEnd": 160}, {"clueNum": 59, "clueStart": 162, "value": "Take home", "clueEnd": 164}, {"clueNum": 60, "clueStart": 167, "value": "Speak hoarsely", "clueEnd": 170}, {"clueNum": 62, "clueStart": 172, "value": "Motormouth ___ (\"Hairspray\" role for Queen Latifah)", "clueEnd": 179}, {"clueNum": 64, "clueStart": 180, "value": "Where sticky fingers might be caught", "clueEnd": 188}, {"clueNum": 67, "clueStart": 190, "value": "Like 48-Downs, to Ireland", "clueEnd": 194, "related": {"down": [48], "across": []}}, {"clueNum": 68, "clueStart": 195, "value": "Eventually brought results", "clueEnd": 203}, {"clueNum": 69, "clueStart": 205, "value": "Section of a long poem", "clueEnd": 209}, {"clueNum": 70, "clueStart": 210, "value": "\"Help!\"", "clueEnd": 212}, {"clueNum": 71, "clueStart": 215, "value": "And so on", "clueEnd": 217}, {"clueNum": 72, "clueStart": 220, "value": "Places for patellas", "clueEnd": 224}], "D": [{"clueNum": 1, "clueStart": 0, "value": "Slings mud at, in a campaign", "clueEnd": 75}, {"clueNum": 2, "clueStart": 1, "value": "Like basketball players vis-\u00e0-vis jockeys, typically", "clueEnd": 76}, {"clueNum": 3, "clueStart": 2, "value": "Ensemble", "clueEnd": 77}, {"clueNum": 4, "clueStart": 3, "value": "Smelly smell", "clueEnd": 48}, {"clueNum": 5, "clueStart": 4, "value": "Brightest light in Cygnus", "clueEnd": 64}, {"clueNum": 6, "clueStart": 7, "value": "Hanukkah centerpiece", "clueEnd": 97}, {"clueNum": 7, "clueStart": 8, "value": "Shape of some curves", "clueEnd": 38}, {"clueNum": 8, "clueStart": 9, "value": "Letters before ://", "clueEnd": 54}, {"clueNum": 9, "clueStart": 12, "value": "Roman goddess who is the equivalent of the Greek Nike", "clueEnd": 117}, {"clueNum": 10, "clueStart": 13, "value": "Bit of yoga equipment", "clueEnd": 43}, {"clueNum": 11, "clueStart": 14, "value": "Ice Bucket Challenge cause, for short", "clueEnd": 44}, {"clueNum": 13, "clueStart": 21, "value": "Clergy member", "clueEnd": 81}, {"clueNum": 14, "clueStart": 25, "value": "Bluish-purple flower", "clueEnd": 70}, {"clueNum": 15, "clueStart": 26, "value": "Aldo of fashion", "clueEnd": 86}, {"clueNum": 19, "clueStart": 50, "value": "Common recyclable", "clueEnd": 140}, {"clueNum": 23, "clueStart": 68, "value": "Feature (in)", "clueEnd": 113}, {"clueNum": 25, "clueStart": 73, "value": "Malek of \"Mr. Robot\"", "clueEnd": 118}, {"clueNum": 26, "clueStart": 74, "value": "Channel for armchair athletes", "clueEnd": 119}, {"clueNum": 28, "clueStart": 78, "value": "Paid spots", "clueEnd": 108}, {"clueNum": 30, "clueStart": 84, "value": "Pass without notice", "clueEnd": 174}, {"clueNum": 33, "clueStart": 94, "value": "An aye for the eye?", "clueEnd": 124}, {"clueNum": 35, "clueStart": 100, "value": "Gateway to the West, on scoreboards", "clueEnd": 130}, {"clueNum": 37, "clueStart": 105, "value": "Ugly beast", "clueEnd": 150}, {"clueNum": 38, "clueStart": 106, "value": "Justice Gorsuch", "clueEnd": 151}, {"clueNum": 39, "clueStart": 107, "value": "Rulers of the Aztecs and Incas", "clueEnd": 212}, {"clueNum": 40, "clueStart": 111, "value": "Door handle", "clueEnd": 156}, {"clueNum": 42, "clueStart": 116, "value": "Cleaning cloth", "clueEnd": 146}, {"clueNum": 45, "clueStart": 127, "value": "Language of ancient Syria", "clueEnd": 217}, {"clueNum": 48, "clueStart": 138, "value": "Creature that grows longer in a classic video game (also in this puzzle, when it \"eats\" a black square)", "clueEnd": 198, "related": {"down": [], "across": [13, 67]}}, {"clueNum": 50, "clueStart": 143, "value": "Like many appliances in modern homes", "clueEnd": 203}, {"clueNum": 52, "clueStart": 147, "value": "Where one might be represented by an avatar", "clueEnd": 222}, {"clueNum": 53, "clueStart": 148, "value": "Erase", "clueEnd": 223}, {"clueNum": 54, "clueStart": 149, "value": "Transcription pros", "clueEnd": 224}, {"clueNum": 56, "clueStart": 154, "value": "\"In your dreams!\"", "clueEnd": 199}, {"clueNum": 58, "clueStart": 160, "value": "One way to be taken", "clueEnd": 220}, {"clueNum": 61, "clueStart": 170, "value": "Parisian papa", "clueEnd": 215}, {"clueNum": 63, "clueStart": 176, "value": "Panache", "clueEnd": 221}, {"clueNum": 64, "clueStart": 180, "value": "\"Sunday Morning\" airer", "clueEnd": 210}, {"clueNum": 65, "clueStart": 181, "value": "Away from work, for short", "clueEnd": 211}, {"clueNum": 66, "clueStart": 186, "value": "Stick (out)", "clueEnd": 216}]}, "clueListOrder": ["Across", "Down"], "layout": [1, 1, 1, 1, 1, 0, 0, 1, 1, 1, 0, 0, 1, 1, 1, 1, 1, 1, 1, 1, 0, 1, 1, 1, 1, 1, 1, 1, 1, 1, 1, 1, 1, 1, 1, 0, 1, 9, 9, 9, 9, 1, 1, 1, 1, 1, 1, 1, 1, 1, 1, 9, 9, 0, 1, 9, 9, 9, 0, 0, 1, 1, 1, 0, 9, 9, 9, 1, 1, 0, 1, 1, 9, 1, 1, 1, 1, 1, 9, 0, 1, 1, 1, 1, 1, 0, 1, 9, 1, 1, 0, 0, 0, 9, 9, 1, 0, 1, 1, 1, 1, 0, 1, 1, 1, 1, 1, 1, 1, 9, 9, 1, 0, 9, 9, 9, 9, 1, 1, 1, 1, 1, 1, 0, 1, 9, 9, 9, 0, 1, 1, 9, 0, 0, 0, 1, 1, 1, 1, 0, 1, 1, 1, 1, 1, 0, 9, 1, 1, 1, 1, 1, 1, 1, 1, 0, 1, 1, 9, 9, 9, 0, 1, 1, 1, 0, 0, 1, 9, 9, 9, 0, 9, 9, 1, 1, 1, 1, 1, 1, 1, 1, 1, 1, 1, 1, 1, 1, 1, 0, 1, 1, 1, 1, 1, 1, 1, 1, 1, 1, 1, 1, 1, 1, 0, 1, 1, 1, 1, 1, 1, 1, 1, 0, 0, 1, 1, 1, 0, 0, 1, 1, 1, 1, 1], "answers": []}}