{"puzzle_id": 21418, "promo_id": null, "version": 0, "puzzle_meta": {"formatType": "Normal", "publishType": "Daily", "title": "", "printDate": "2023-10-27", "printDotw": 5, "editor": "Will Shortz", "copyright": "", "height": 15, "width": 15, "notes": [], "links": [], "layoutExtra": [], "author": "Adrian Johnson", "relatedContent": {"text": "Read and comment on the Wordplay blog", "url": "https://www.nytimes.com/2023/10/26/crosswords/daily-puzzle-2023-10-27.html"}}, "print_date": "2023-10-27", "enhanced_tier_date": null, "authors": ["Adrian Johnson"], "puzzle_data": {"clues": {"A": [{"clueNum": 1, "clueStart": 1, "value": "\"Award\" bestowed at the Kids' Choice Awards", "clueEnd": 5}, {"clueNum": 6, "clueStart": 7, "value": "Garter and stockinette, in knitting", "clueEnd": 14}, {"clueNum": 14, "clueStart": 15, "value": "Outbreaks", "clueEnd": 20}, {"clueNum": 15, "clueStart": 22, "value": "Admonishment from Austin Powers", "clueEnd": 29}, {"clueNum": 16, "clueStart": 30, "value": "Took on a pet project?", "clueEnd": 35}, {"clueNum": 17, "clueStart": 37, "value": "\"All rise\" reversal", "clueEnd": 44}, {"clueNum": 18, "clueStart": 45, "value": "\"Things ___ that simple\"", "clueEnd": 49}, {"clueNum": 19, "clueStart": 51, "value": "Novelist whose \"Little Fires Everywhere\" became a #1 best seller", "clueEnd": 59}, {"clueNum": 20, "clueStart": 60, "value": "It was called Big Meadows on the California Trail", "clueEnd": 63}, {"clueNum": 21, "clueStart": 65, "value": "Bird whose largest species is called the Goliath", "clueEnd": 69}, {"clueNum": 22, "clueStart": 72, "value": "66, e.g.: Abbr.", "clueEnd": 74}, {"clueNum": 23, "clueStart": 75, "value": "Casual Friday gaffe", "clueEnd": 78}, {"clueNum": 24, "clueStart": 80, "value": "Self starter?", "clueEnd": 83}, {"clueNum": 25, "clueStart": 85, "value": "Slight contact, on a pool table", "clueEnd": 88}, {"clueNum": 27, "clueStart": 91, "value": "Like either main face of El Capitan", "clueEnd": 95}, {"clueNum": 29, "clueStart": 97, "value": "Lightened up?", "clueEnd": 101}, {"clueNum": 31, "clueStart": 107, "value": "Stand near a poser", "clueEnd": 111}, {"clueNum": 33, "clueStart": 113, "value": "Element exhibiting a blue glow when placed in an electric field", "clueEnd": 117}, {"clueNum": 35, "clueStart": 123, "value": "Unclothe", "clueEnd": 127}, {"clueNum": 37, "clueStart": 129, "value": "Like the bonds of table salt", "clueEnd": 133}, {"clueNum": 39, "clueStart": 136, "value": "Actor Diggs", "clueEnd": 139}, {"clueNum": 41, "clueStart": 141, "value": "Scaloppine option", "clueEnd": 144}, {"clueNum": 43, "clueStart": 146, "value": "Word before and after \"\u2018s\"", "clueEnd": 149}, {"clueNum": 45, "clueStart": 150, "value": "\"House\" band?: Abbr.", "clueEnd": 152}, {"clueNum": 46, "clueStart": 155, "value": "Its population doubles once a year", "clueEnd": 159}, {"clueNum": 47, "clueStart": 161, "value": "Barossa Valley export", "clueEnd": 164}, {"clueNum": 48, "clueStart": 165, "value": "Bibimbap and tamago kake gohan, for two ", "clueEnd": 173}, {"clueNum": 51, "clueStart": 175, "value": "Shire who played a Corleone", "clueEnd": 179}, {"clueNum": 52, "clueStart": 180, "value": "Popular Schubert composition", "clueEnd": 187}, {"clueNum": 53, "clueStart": 189, "value": "Single-minded philosophy", "clueEnd": 194}, {"clueNum": 54, "clueStart": 195, "value": "Features of many hotel rooms", "clueEnd": 202}, {"clueNum": 55, "clueStart": 204, "value": "Gets ready to dry, say", "clueEnd": 209}, {"clueNum": 56, "clueStart": 210, "value": "\"Alas, it is so\"", "clueEnd": 217}, {"clueNum": 57, "clueStart": 219, "value": "Group of runners?", "clueEnd": 223}], "D": [{"clueNum": 1, "clueStart": 1, "value": "\"We've heard enough of this nonsense\"", "clueEnd": 91}, {"clueNum": 2, "clueStart": 2, "value": "Like some TV talk shows, informally", "clueEnd": 107}, {"clueNum": 3, "clueStart": 3, "value": "\"There's a lot more to this than you think\"", "clueEnd": 138}, {"clueNum": 4, "clueStart": 4, "value": "Heart", "clueEnd": 49}, {"clueNum": 5, "clueStart": 5, "value": "Contractor's fig.", "clueEnd": 35}, {"clueNum": 6, "clueStart": 7, "value": "Get serious, in a way", "clueEnd": 97}, {"clueNum": 7, "clueStart": 8, "value": "Children's story with Truffula Trees", "clueEnd": 113}, {"clueNum": 8, "clueStart": 9, "value": "Playwright awarded the Grand Cross of the Order of St. Olav in 1893", "clueEnd": 69}, {"clueNum": 9, "clueStart": 10, "value": "Links things", "clueEnd": 55}, {"clueNum": 10, "clueStart": 11, "value": "Jaw", "clueEnd": 56}, {"clueNum": 11, "clueStart": 12, "value": "Unfriendly crowd", "clueEnd": 87}, {"clueNum": 12, "clueStart": 13, "value": "Goings-on", "clueEnd": 88}, {"clueNum": 13, "clueStart": 14, "value": "Plant growing in tufts", "clueEnd": 74}, {"clueNum": 14, "clueStart": 15, "value": "Results of cuts, maybe", "clueEnd": 75}, {"clueNum": 19, "clueStart": 51, "value": "Lead runner, for short?", "clueEnd": 81}, {"clueNum": 21, "clueStart": 65, "value": "Really excited", "clueEnd": 125}, {"clueNum": 25, "clueStart": 85, "value": "Game whose name comes from French for \"five winning numbers\"", "clueEnd": 130}, {"clueNum": 26, "clueStart": 86, "value": "Response from one who ain't gonna", "clueEnd": 221}, {"clueNum": 28, "clueStart": 94, "value": "90\u00b0 from norte", "clueEnd": 139}, {"clueNum": 30, "clueStart": 99, "value": "Actress George of \"Animal Kingdom\"", "clueEnd": 159}, {"clueNum": 32, "clueStart": 111, "value": "Volatile personality", "clueEnd": 216}, {"clueNum": 34, "clueStart": 117, "value": "One who might say \"Nothing is real\"", "clueEnd": 222}, {"clueNum": 36, "clueStart": 127, "value": "It might conclude with a shower, informally", "clueEnd": 217}, {"clueNum": 38, "clueStart": 133, "value": "\"Care to show me?\"", "clueEnd": 223}, {"clueNum": 39, "clueStart": 136, "value": "Pub ___", "clueEnd": 211}, {"clueNum": 40, "clueStart": 137, "value": "Climb", "clueEnd": 212}, {"clueNum": 42, "clueStart": 143, "value": "Heat extractors, for short", "clueEnd": 173}, {"clueNum": 44, "clueStart": 149, "value": "Devils and Angels, e.g.", "clueEnd": 209}, {"clueNum": 45, "clueStart": 150, "value": "Apothecary measures", "clueEnd": 210}, {"clueNum": 46, "clueStart": 155, "value": "Cooperative hunter with the coral grouper", "clueEnd": 215}, {"clueNum": 49, "clueStart": 168, "value": "Romanian philosopher Cioran", "clueEnd": 213}, {"clueNum": 50, "clueStart": 169, "value": "Miniature", "clueEnd": 214}, {"clueNum": 51, "clueStart": 175, "value": "Labor", "clueEnd": 220}, {"clueNum": 53, "clueStart": 189, "value": "\"___ Davis\" (series starring Betty Gilpin)", "clueEnd": 219}]}, "clueListOrder": ["Across", "Down"], "layout": [0, 1, 1, 1, 1, 1, 0, 1, 1, 1, 1, 1, 1, 1, 1, 1, 1, 1, 1, 1, 1, 0, 1, 1, 1, 1, 1, 1, 1, 1, 1, 1, 1, 1, 1, 1, 0, 1, 1, 1, 1, 1, 1, 1, 1, 1, 1, 1, 1, 1, 0, 1, 1, 1, 1, 1, 1, 1, 1, 1, 1, 1, 1, 1, 0, 1, 1, 1, 1, 1, 0, 0, 1, 1, 1, 1, 1, 1, 1, 0, 1, 1, 1, 1, 0, 1, 1, 1, 1, 0, 0, 1, 1, 1, 1, 1, 0, 1, 1, 1, 1, 1, 0, 0, 0, 0, 0, 1, 1, 1, 1, 1, 0, 1, 1, 1, 1, 1, 0, 0, 0, 0, 0, 1, 1, 1, 1, 1, 0, 1, 1, 1, 1, 1, 0, 0, 1, 1, 1, 1, 0, 1, 1, 1, 1, 0, 1, 1, 1, 1, 1, 1, 1, 0, 0, 1, 1, 1, 1, 1, 0, 1, 1, 1, 1, 1, 1, 1, 1, 1, 1, 1, 1, 1, 0, 1, 1, 1, 1, 1, 1, 1, 1, 1, 1, 1, 1, 1, 0, 1, 1, 1, 1, 1, 1, 1, 1, 1, 1, 1, 1, 1, 1, 0, 1, 1, 1, 1, 1, 1, 1, 1, 1, 1, 1, 1, 1, 1, 0, 1, 1, 1, 1, 1, 0], "answers": []}}