{"puzzle_id": 21103, "promo_id": null, "version": 0, "puzzle_meta": {"formatType": "Normal", "publishType": "Daily", "title": "", "printDate": "2023-06-26", "printDotw": 1, "editor": "Will Shortz", "copyright": "", "height": 15, "width": 15, "notes": [], "links": [], "layoutExtra": [], "author": "Taylor Johnson and Christina Iverson", "relatedContent": {"text": "Read and comment on the Wordplay blog", "url": "https://www.nytimes.com/2023/06/25/crosswords/daily-puzzle-2023-06-26.html"}}, "print_date": "2023-06-26", "enhanced_tier_date": null, "authors": ["Taylor Johnson and Christina Iverson"], "puzzle_data": {"clues": {"A": [{"clueNum": 1, "clueStart": 0, "value": "Back of the neck", "clueEnd": 3}, {"clueNum": 5, "clueStart": 5, "value": "Window covering with adjustable slats", "clueEnd": 9}, {"clueNum": 10, "clueStart": 11, "value": "Bakery or bookstore", "clueEnd": 14}, {"clueNum": 14, "clueStart": 15, "value": "Big brand in skin care", "clueEnd": 18}, {"clueNum": 15, "clueStart": 20, "value": "___ the Riveter (woman in an old wartime poster)", "clueEnd": 24}, {"clueNum": 16, "clueStart": 26, "value": "Give up", "clueEnd": 29}, {"clueNum": 17, "clueStart": 30, "value": "One growing asparagus, spinach, corn, etc.", "clueEnd": 44, "related": {"down": [], "across": [61]}}, {"clueNum": 20, "clueStart": 45, "value": "\"You ___ Beautiful\" (Joe Cocker classic)", "clueEnd": 49}, {"clueNum": 21, "clueStart": 51, "value": "Brief unit of time: Abbr.", "clueEnd": 53}, {"clueNum": 22, "clueStart": 55, "value": "Believer in a non-intervening God", "clueEnd": 59}, {"clueNum": 23, "clueStart": 61, "value": "Familiar clich\u00e9 in storytelling, like \"the love triangle\" or \"the girl next door\"", "clueEnd": 65}, {"clueNum": 25, "clueStart": 67, "value": "Agreeable suck-ups", "clueEnd": 72}, {"clueNum": 27, "clueStart": 78, "value": "Minor criticisms", "clueEnd": 81}, {"clueNum": 29, "clueStart": 84, "value": "Regal, in a way", "clueEnd": 89}, {"clueNum": 32, "clueStart": 90, "value": "Squad leader, in sports", "clueEnd": 100, "related": {"down": [], "across": [61]}}, {"clueNum": 37, "clueStart": 102, "value": "Deep sorrow", "clueEnd": 104}, {"clueNum": 38, "clueStart": 105, "value": "Clearasil target", "clueEnd": 108}, {"clueNum": 39, "clueStart": 111, "value": "\"___ Not Your Negro\" (2016 documentary using James Baldwin texts)", "clueEnd": 113}, {"clueNum": 40, "clueStart": 116, "value": "Storybook bear whose porridge was too cold", "clueEnd": 119}, {"clueNum": 41, "clueStart": 120, "value": "Often-spiked holiday beverage, familiarly", "clueEnd": 122}, {"clueNum": 42, "clueStart": 124, "value": "Certain bluegrass musician", "clueEnd": 134, "related": {"down": [], "across": [61]}}, {"clueNum": 46, "clueStart": 135, "value": "Garden figurines with beards and pointy hats", "clueEnd": 140}, {"clueNum": 48, "clueStart": 143, "value": "Search for", "clueEnd": 146}, {"clueNum": 49, "clueStart": 152, "value": "Bit of tennis or squash equipment", "clueEnd": 157}, {"clueNum": 52, "clueStart": 159, "value": "Representative", "clueEnd": 163}, {"clueNum": 55, "clueStart": 165, "value": "Danger in \"Jaws\"", "clueEnd": 169}, {"clueNum": 57, "clueStart": 171, "value": "Language related to Thai", "clueEnd": 173}, {"clueNum": 59, "clueStart": 175, "value": "The \"U\" of E.U.", "clueEnd": 179}, {"clueNum": 61, "clueStart": 180, "value": "\"So particular!\" \u2026 or, in different senses, like 17-, 32- and 42-Across?", "clueEnd": 194, "related": {"down": [], "across": [42, 17, 32, 42]}}, {"clueNum": 64, "clueStart": 195, "value": "Common racetrack shape", "clueEnd": 198}, {"clueNum": 65, "clueStart": 200, "value": "Ones downloading and accessing apps", "clueEnd": 204}, {"clueNum": 66, "clueStart": 206, "value": "Julie ___ Moonves, \"Big Brother\" host", "clueEnd": 209}, {"clueNum": 67, "clueStart": 210, "value": "Head, in French", "clueEnd": 213}, {"clueNum": 68, "clueStart": 215, "value": "Floral potpourri piece", "clueEnd": 219}, {"clueNum": 69, "clueStart": 221, "value": "Little bitty", "clueEnd": 224}], "D": [{"clueNum": 1, "clueStart": 0, "value": "PBS science series since 1974", "clueEnd": 45}, {"clueNum": 2, "clueStart": 1, "value": "Cellphone notification", "clueEnd": 61}, {"clueNum": 3, "clueStart": 2, "value": "On-call doctor's summoning device", "clueEnd": 62}, {"clueNum": 4, "clueStart": 3, "value": "\"Pay full attention while I'm talking!\"", "clueEnd": 108}, {"clueNum": 5, "clueStart": 5, "value": "Bikini top", "clueEnd": 35}, {"clueNum": 6, "clueStart": 6, "value": "High tennis shots", "clueEnd": 51}, {"clueNum": 7, "clueStart": 7, "value": "The ___ Brothers (\"It's Your Thing\" group)", "clueEnd": 67}, {"clueNum": 8, "clueStart": 8, "value": "Nephew's counterpart", "clueEnd": 68}, {"clueNum": 9, "clueStart": 9, "value": "Hi-___ TV", "clueEnd": 39}, {"clueNum": 10, "clueStart": 11, "value": "Cinema unit", "clueEnd": 86}, {"clueNum": 11, "clueStart": 12, "value": "Ernest who wrote \"A Farewell to Arms\"", "clueEnd": 132}, {"clueNum": 12, "clueStart": 13, "value": "Poems of dedication", "clueEnd": 58}, {"clueNum": 13, "clueStart": 14, "value": "Sassy", "clueEnd": 59}, {"clueNum": 18, "clueStart": 34, "value": "Subject to discuss", "clueEnd": 94}, {"clueNum": 19, "clueStart": 40, "value": "Web page moderator, for short", "clueEnd": 100}, {"clueNum": 24, "clueStart": 65, "value": "GPS prediction based on distance and driving speed", "clueEnd": 95}, {"clueNum": 26, "clueStart": 69, "value": "Hit the slopes", "clueEnd": 99}, {"clueNum": 28, "clueStart": 81, "value": "Twirl", "clueEnd": 126}, {"clueNum": 30, "clueStart": 88, "value": "Togo's capital", "clueEnd": 133}, {"clueNum": 31, "clueStart": 89, "value": "Wine label information", "clueEnd": 134}, {"clueNum": 32, "clueStart": 90, "value": "Powdered orange drink", "clueEnd": 135}, {"clueNum": 33, "clueStart": 91, "value": "Subj. that studies financial trends", "clueEnd": 136}, {"clueNum": 34, "clueStart": 92, "value": "Feline with a very fluffy coat", "clueEnd": 212}, {"clueNum": 35, "clueStart": 97, "value": "___ Mahal", "clueEnd": 127}, {"clueNum": 36, "clueStart": 98, "value": "Grammy-nominated singer/songwriter Tori", "clueEnd": 143}, {"clueNum": 40, "clueStart": 116, "value": "Act friendly despite feeling otherwise", "clueEnd": 221}, {"clueNum": 42, "clueStart": 124, "value": "Girl whom Tom Sawyer loves", "clueEnd": 184}, {"clueNum": 43, "clueStart": 125, "value": "Inquire", "clueEnd": 155}, {"clueNum": 44, "clueStart": 129, "value": "Split ___ soup", "clueEnd": 159}, {"clueNum": 45, "clueStart": 130, "value": "Advantage", "clueEnd": 190}, {"clueNum": 47, "clueStart": 138, "value": "Meghan ___, Duchess of Sussex", "clueEnd": 213}, {"clueNum": 50, "clueStart": 156, "value": "Beethoven's \"F\u00fcr ___\"", "clueEnd": 216}, {"clueNum": 51, "clueStart": 157, "value": "\"Be silent,\" in music", "clueEnd": 217}, {"clueNum": 53, "clueStart": 162, "value": "Specialized area of expertise", "clueEnd": 222}, {"clueNum": 54, "clueStart": 163, "value": "Arcade game coin", "clueEnd": 223}, {"clueNum": 55, "clueStart": 165, "value": "Apt name for a Dalmatian", "clueEnd": 210}, {"clueNum": 56, "clueStart": 166, "value": "Place of busy activity", "clueEnd": 211}, {"clueNum": 58, "clueStart": 173, "value": "Pod ingredient in gumbo", "clueEnd": 218}, {"clueNum": 60, "clueStart": 179, "value": "Big Apple address abbr.", "clueEnd": 224}, {"clueNum": 62, "clueStart": 185, "value": "Baby seal", "clueEnd": 215}, {"clueNum": 63, "clueStart": 189, "value": "Fashion monogram", "clueEnd": 219}]}, "clueListOrder": ["Across", "Down"], "layout": [1, 1, 1, 1, 0, 1, 1, 1, 1, 1, 0, 1, 1, 1, 1, 1, 1, 1, 1, 0, 1, 1, 1, 1, 1, 0, 1, 1, 1, 1, 1, 1, 1, 1, 1, 1, 1, 1, 1, 1, 1, 1, 1, 1, 1, 1, 1, 1, 1, 1, 0, 1, 1, 1, 0, 1, 1, 1, 1, 1, 0, 1, 1, 1, 1, 1, 0, 1, 1, 1, 1, 1, 1, 0, 0, 0, 0, 0, 1, 1, 1, 1, 0, 0, 1, 1, 1, 1, 1, 1, 1, 1, 1, 1, 1, 1, 1, 1, 1, 1, 1, 0, 1, 1, 1, 1, 1, 1, 1, 0, 0, 1, 1, 1, 0, 0, 1, 1, 1, 1, 1, 1, 1, 0, 1, 1, 1, 1, 1, 1, 1, 1, 1, 1, 1, 1, 1, 1, 1, 1, 1, 0, 0, 1, 1, 1, 1, 0, 0, 0, 0, 0, 1, 1, 1, 1, 1, 1, 0, 1, 1, 1, 1, 1, 0, 1, 1, 1, 1, 1, 0, 1, 1, 1, 0, 1, 1, 1, 1, 1, 1, 1, 1, 1, 1, 1, 1, 1, 1, 1, 1, 1, 1, 1, 1, 1, 1, 1, 1, 0, 1, 1, 1, 1, 1, 0, 1, 1, 1, 1, 1, 1, 1, 1, 0, 1, 1, 1, 1, 1, 0, 1, 1, 1, 1], "answers": []}}